source_hubspot/__init__.py
source_hubspot/components.py
source_hubspot/constants.py
source_hubspot/errors.py
source_hubspot/helpers.py
source_hubspot/manifest.yaml
source_hubspot/run.py
source_hubspot/schemas/companies.json
source_hubspot/schemas/contacts.json
source_hubspot/schemas/deal_splits.json
source_hubspot/schemas/deals.json
source_hubspot/schemas/engagements_calls.json
source_hubspot/schemas/engagements_emails.json
source_hubspot/schemas/engagements_meetings.json
source_hubspot/schemas/engagements_notes.json
source_hubspot/schemas/engagements_tasks.json
source_hubspot/schemas/feedback_submissions.json
source_hubspot/schemas/goals.json
source_hubspot/schemas/line_items.json
source_hubspot/schemas/products.json
source_hubspot/schemas/shared/default_event_properties.json
source_hubspot/schemas/tickets.json
source_hubspot/source.py
source_hubspot/spec.yaml
source_hubspot/streams.py
airbyte_source_hubspot-5.7.0.dist-info/METADATA
airbyte_source_hubspot-5.7.0.dist-info/WHEEL
airbyte_source_hubspot-5.7.0.dist-info/entry_points.txt
airbyte_source_hubspot-5.7.0.dist-info/RECORD
